banko
