Metadata-Version: 2.1
Name: banko
Version: 0.1.4
Summary: Library for generating banko plates
Home-page: https://github.com/skipperkongen/banko
Author: Pimin Konstantin Kefaloukos
Author-email: skipperkongen@gmail.com
License: UNKNOWN
Download-URL: https://github.com/skipperkongen/banko/archive/refs/tags/v0.1.4.tar.gz
Platform: UNKNOWN
Classifier: Programming Language :: Python :: 3
Classifier: License :: OSI Approved :: MIT License
Classifier: Operating System :: OS Independent
